plugin.py
corva/__init__.py
corva/api.py
corva/api_utils.py
corva/cache_adapter.py
corva/configuration.py
corva/handlers.py
corva/logger.py
corva/py.typed
corva/shared.py
corva/testing.py
corva/validate_app_init.py
corva/models/__init__.py
corva/models/base.py
corva/models/context.py
corva/models/rerun.py
corva/models/task.py
corva/models/validators.py
corva/models/merge/__init__.py
corva/models/merge/enums.py
corva/models/merge/merge.py
corva/models/merge/raw.py
corva/models/scheduled/__init__.py
corva/models/scheduled/raw.py
corva/models/scheduled/scheduled.py
corva/models/scheduled/scheduler_type.py
corva/models/stream/__init__.py
corva/models/stream/initial.py
corva/models/stream/log_type.py
corva/models/stream/raw.py
corva/models/stream/stream.py
corva/service/__init__.py
corva/service/api_sdk.py
corva/service/cache_sdk.py
corva/service/service.py
corva_sdk-2.0.3.dist-info/METADATA
corva_sdk-2.0.3.dist-info/WHEEL
corva_sdk-2.0.3.dist-info/entry_points.txt
corva_sdk-2.0.3.dist-info/top_level.txt
corva_sdk-2.0.3.dist-info/RECORD
